django_commonutil_restframework.py
django_commonutil_restframework-0.3.1.dist-info/METADATA
django_commonutil_restframework-0.3.1.dist-info/WHEEL
django_commonutil_restframework-0.3.1.dist-info/top_level.txt
django_commonutil_restframework-0.3.1.dist-info/RECORD
