Metadata-Version: 2.1
Name: django-commonutil-restframework
Version: 0.3.1
Summary: Common utilities for Django REST Framework
License: MIT License
Platform: UNKNOWN
Classifier: Development Status :: 5 - Production/Stable
Classifier: Intended Audience :: Developers
Classifier: License :: OSI Approved :: MIT License
Classifier: Programming Language :: Python :: 3.7
Classifier: Framework :: Django :: 3.2
